orders_pr_messaging/__init__.py
orders_pr_messaging/connection.py
orders_pr_messaging/dto.py
orders_pr_messaging-0.2.0.dist-info/METADATA
orders_pr_messaging-0.2.0.dist-info/WHEEL
orders_pr_messaging-0.2.0.dist-info/top_level.txt
orders_pr_messaging-0.2.0.dist-info/RECORD
