Metadata-Version: 2.1
Name: orders-pr-messaging
Version: 0.2.0
Summary: orders system common messaging
Author: Viktor
Author-email: test@mail.com
Requires-Dist: aio-pika (==8.3.0)
Requires-Dist: pika (==1.3.1)
